wildgram/__init__.py
wildgram/magicrules.py
wildgram/tobedeleted.py
wildgram/wildgram.py
wildgram-0.5.7.dist-info/LICENSE
wildgram-0.5.7.dist-info/METADATA
wildgram-0.5.7.dist-info/WHEEL
wildgram-0.5.7.dist-info/top_level.txt
wildgram-0.5.7.dist-info/RECORD
