Metadata-Version: 2.1
Name: wildgram
Version: 0.5.7
Summary: wildgram tokenizes and seperates tokens into ngrams of varying size based on the natural language breaks in the text.
Home-page: https://gitlab.com/gracekatherineturner/wildgram
Author: Grace Turner
Author-email: gracekatherineturner@gmail.com
License: UNKNOWN
Platform: UNKNOWN
Classifier: Programming Language :: Python :: 3
Classifier: License :: OSI Approved :: MIT License
Classifier: Operating System :: OS Independent
Requires-Python: >=3.6
